ns_gym/.DS_Store
ns_gym/__init__.py
ns_gym/base.py
ns_gym/context_switching.py
ns_gym/schedulers.py
ns_gym/utils.py
ns_gym/benchmark_algorithms/.DS_Store
ns_gym/benchmark_algorithms/DDPG.py
ns_gym/benchmark_algorithms/MCTS.py
ns_gym/benchmark_algorithms/PAMCTS.py
ns_gym/benchmark_algorithms/__init__.py
ns_gym/benchmark_algorithms/algo_utils.py
ns_gym/benchmark_algorithms/ActAsYouLearn/BayesianNeuralNetwork.py
ns_gym/benchmark_algorithms/ActAsYouLearn/BayesianNeuralNetwork_od.py
ns_gym/benchmark_algorithms/ActAsYouLearn/ExperienceReplay.py
ns_gym/benchmark_algorithms/ActAsYouLearn/HiPMDP.py
ns_gym/benchmark_algorithms/ActAsYouLearn/PriorityQueue.py
ns_gym/benchmark_algorithms/ActAsYouLearn/Qnetwork.py
ns_gym/benchmark_algorithms/ActAsYouLearn/README.md
ns_gym/benchmark_algorithms/ActAsYouLearn/__init__.py
ns_gym/benchmark_algorithms/ActAsYouLearn/all_transitions_0.4.pkl
ns_gym/benchmark_algorithms/ActAsYouLearn/check_LC.py
ns_gym/benchmark_algorithms/ActAsYouLearn/compute_distance.py
ns_gym/benchmark_algorithms/ActAsYouLearn/data_generation.py
ns_gym/benchmark_algorithms/ActAsYouLearn/main.py
ns_gym/benchmark_algorithms/ActAsYouLearn/mcts.py
ns_gym/benchmark_algorithms/ActAsYouLearn/mcts_model.py
ns_gym/benchmark_algorithms/ActAsYouLearn/mcts_standard.py
ns_gym/benchmark_algorithms/ActAsYouLearn/mcts_t.py
ns_gym/benchmark_algorithms/ActAsYouLearn/plot.py
ns_gym/benchmark_algorithms/ActAsYouLearn/plot_uncertainties.py
ns_gym/benchmark_algorithms/ActAsYouLearn/results_fintune_frozen1_0.7in1_threshold.txt
ns_gym/benchmark_algorithms/ActAsYouLearn/step_training_record_seed_3
ns_gym/benchmark_algorithms/ActAsYouLearn/steps_record
ns_gym/benchmark_algorithms/ActAsYouLearn/temp_result
ns_gym/benchmark_algorithms/ActAsYouLearn/time_record
ns_gym/benchmark_algorithms/ActAsYouLearn/train_model.py
ns_gym/benchmark_algorithms/ActAsYouLearn/training_record_seed_3
ns_gym/benchmark_algorithms/ActAsYouLearn/data_buffer/frozenlake_0_exp_buffer
ns_gym-1.0.7.dist-info/licenses/LICENSE
ns_gym-1.0.7.dist-info/licenses/NOTICE
ns_gym-1.0.7.dist-info/METADATA
ns_gym-1.0.7.dist-info/WHEEL
ns_gym-1.0.7.dist-info/top_level.txt
ns_gym-1.0.7.dist-info/RECORD
