Metadata-Version: 2.4
Name: ns_gym
Version: 1.0.7
Summary: A simulation toolkit for non-stationary Markov decision processes
License-Expression: MIT
Project-URL: Homepage, https://nsgym.io/
Project-URL: Issues, https://github.com/scope-lab-vu/ns_gym/issues
Project-URL: Repo, https://github.com/scope-lab-vu/ns_gym
Classifier: Programming Language :: Python :: 3
Classifier: Operating System :: OS Independent
Requires-Python: >=3.10
License-File: LICENSE
License-File: NOTICE
Requires-Dist: numpy>=1.26.4
Requires-Dist: gymnasium[mujoco]
Requires-Dist: mujoco<3.4,>=3.3
Requires-Dist: pygame
Requires-Dist: torch
Requires-Dist: scipy
Requires-Dist: matplotlib
Requires-Dist: tensorboard
Requires-Dist: pyyaml
Requires-Dist: pandas
Requires-Dist: stable_baselines3[extra]
Provides-Extra: dev
Requires-Dist: pytest; extra == "dev"
Requires-Dist: pytest-cov; extra == "dev"
Requires-Dist: sphinx; extra == "dev"
Requires-Dist: myst-parser; extra == "dev"
Requires-Dist: sphinx-rtd-theme; extra == "dev"
Requires-Dist: sphinx-autodoc-typehints; extra == "dev"
Requires-Dist: shibuya; extra == "dev"
Requires-Dist: nbsphinx; extra == "dev"
Requires-Dist: ipykernel; extra == "dev"
Requires-Dist: myst_nb; extra == "dev"
Requires-Dist: sphinx-math-dollar; extra == "dev"
Requires-Dist: tox; extra == "dev"
Requires-Dist: tox-uv; extra == "dev"
Provides-Extra: all
Requires-Dist: ns_gym[dev]; extra == "all"
Dynamic: license-file
